boamp/__init__.py
boamp/__main__.py
boamp/cache.py
boamp/cli.py
boamp/models.py
boamp/pagination.py
boamp/rate_limiter.py
boamp/scraper.py
boamp_scraper-0.2.0.dist-info/licenses/AUTHORS.md
boamp_scraper-0.2.0.dist-info/licenses/LICENSE
boamp_scraper-0.2.0.dist-info/METADATA
boamp_scraper-0.2.0.dist-info/WHEEL
boamp_scraper-0.2.0.dist-info/top_level.txt
boamp_scraper-0.2.0.dist-info/RECORD
