Metadata-Version: 2.4
Name: boamp-scraper
Version: 0.2.0
Summary: Scrape French public tenders (BOAMP) in 3 lines of Python
Home-page: https://github.com/algora/boamp-scraper
Author: Algora
Author-email: Algora <contact@algora.fr>
License: MIT
Project-URL: Homepage, https://github.com/Ouailleme/boamp-scraper
Project-URL: Documentation, https://github.com/Ouailleme/boamp-scraper#readme
Project-URL: Repository, https://github.com/Ouailleme/boamp-scraper
Project-URL: Bug Tracker, https://github.com/Ouailleme/boamp-scraper/issues
Keywords: boamp,scraper,france,tenders,public-procurement,marchés-publics
Classifier: Development Status :: 3 - Alpha
Classifier: Intended Audience :: Developers
Classifier: Topic :: Software Development :: Libraries :: Python Modules
Classifier: License :: OSI Approved :: MIT License
Classifier: Programming Language :: Python :: 3
Classifier: Programming Language :: Python :: 3.10
Classifier: Programming Language :: Python :: 3.11
Classifier: Programming Language :: Python :: 3.12
Requires-Python: >=3.10
License-File: LICENSE
License-File: AUTHORS.md
Requires-Dist: playwright>=1.41.0
Requires-Dist: beautifulsoup4>=4.12.0
Requires-Dist: lxml>=5.1.0
Requires-Dist: aiohttp>=3.9.0
Requires-Dist: pydantic>=2.5.0
Requires-Dist: python-dotenv>=1.0.0
Requires-Dist: fake-useragent>=1.5.0
Provides-Extra: dev
Requires-Dist: pytest>=7.4.0; extra == "dev"
Requires-Dist: pytest-asyncio>=0.21.0; extra == "dev"
Requires-Dist: pytest-cov>=4.1.0; extra == "dev"
Requires-Dist: black>=23.7.0; extra == "dev"
Requires-Dist: mypy>=1.4.0; extra == "dev"
Requires-Dist: ruff>=0.0.285; extra == "dev"
Dynamic: author
Dynamic: home-page
Dynamic: license-file
Dynamic: requires-python
